webcore/__init__.py
webcore/api_encoder.py
webcore/base_model.py
webcore/cache.py
webcore/constant.py
webcore/error_handler.py
webcore/exception.py
webcore/graphql.py
webcore/gt_flask.py
webcore/http_request.py
webcore/interceptor.py
webcore/mongo_encoder.py
webcore/permission.py
webcore/processor.py
webcore/request_parser.py
webcore/result.py
webcore/sql_encoder.py
webcore/transaction.py
webcore/utils.py
gt_webcore-0.2.9.dist-info/LICENSE
gt_webcore-0.2.9.dist-info/METADATA
gt_webcore-0.2.9.dist-info/WHEEL
gt_webcore-0.2.9.dist-info/top_level.txt
gt_webcore-0.2.9.dist-info/RECORD
