Metadata-Version: 2.1
Name: gt-webcore
Version: 0.2.9
Summary: A Web Service Framework Base On Flask And Sqlalchemy
Home-page: https://github.com/Genetalks/gt-webcore
Author: wunan
Author-email: wunan799@163.com
License: MIT
Keywords: flask,sqlalchemy,restful
Platform: UNKNOWN
Classifier: Development Status :: 5 - Production/Stable
Classifier: Intended Audience :: Developers
Classifier: License :: OSI Approved :: MIT License
Classifier: Topic :: Database
Classifier: Topic :: Software Development :: Libraries
Classifier: Programming Language :: Python
Classifier: Programming Language :: Python :: 3
Classifier: Programming Language :: Python :: 3.6
Requires-Dist: Flask-Cors (>=3.0.8)
Requires-Dist: Flask (>=1.1.2)
Requires-Dist: flask-restful
Requires-Dist: flexible-dotdict
Requires-Dist: requests
